intake_xarray/__init__.py
intake_xarray/_version.py
intake_xarray/base.py
intake_xarray/derived.py
intake_xarray/image.py
intake_xarray/netcdf.py
intake_xarray/opendap.py
intake_xarray/raster.py
intake_xarray/xarray_container.py
intake_xarray/xzarr.py
intake_xarray/tests/__init__.py
intake_xarray/tests/conftest.py
intake_xarray/tests/test_catalog.py
intake_xarray/tests/test_derived.py
intake_xarray/tests/test_image.py
intake_xarray/tests/test_intake_xarray.py
intake_xarray/tests/test_network.py
intake_xarray/tests/test_remote.py
intake_xarray-0.7.0.dist-info/LICENSE
intake_xarray-0.7.0.dist-info/METADATA
intake_xarray-0.7.0.dist-info/WHEEL
intake_xarray-0.7.0.dist-info/entry_points.txt
intake_xarray-0.7.0.dist-info/top_level.txt
intake_xarray-0.7.0.dist-info/RECORD
