Metadata-Version: 2.1
Name: intake-xarray
Version: 0.7.0
Summary: xarray plugins for Intake
Home-page: https://github.com/intake/intake-xarray
Maintainer: Martin Durant
Maintainer-email: mdurant@anaconda.com
License: BSD
License-File: LICENSE
Requires-Dist: intake (>=0.6.6)
Requires-Dist: xarray (>=02022)
Requires-Dist: zarr
Requires-Dist: dask (>=2.2)
Requires-Dist: netcdf4
Requires-Dist: fsspec (>2022)
Requires-Dist: msgpack
Requires-Dist: requests
